kernl/__init__.py
kernl/banner.py
kernl/version.py
kernl/cli/__init__.py
kernl/cli/cli.py
kernl/dataset_managers/__init__.py
kernl/dataset_managers/dataset_manager_base.py
kernl/dataset_managers/dataset_manager_cli.py
kernl/dataset_managers/dataset_manager_huggingface.py
kernl/dataset_managers/dataset_manager_kaggle.py
kernl/server/__init__.py
kernl/server/kernl_server.py
kernl/server/kernl_server_cli.py
kernl/ssh_client/__init__.py
kernl/ssh_client/ssh_client_base.py
kernl/ssh_client/ssh_client_bitbucket.py
kernl/ssh_client/ssh_client_cli.py
kernl/ssh_client/ssh_client_github.py
kernl/ssh_client/ssh_client_gitlab.py
kernl/utils/__init__.py
kernl/utils/messages.py
kernl-0.4.9.dist-info/licenses/LICENSE
kernl-0.4.9.dist-info/METADATA
kernl-0.4.9.dist-info/WHEEL
kernl-0.4.9.dist-info/entry_points.txt
kernl-0.4.9.dist-info/top_level.txt
kernl-0.4.9.dist-info/RECORD
